Metadata-Version: 1.2
Name: pypipkg
Version: 0.0-dev0
Summary: Package Dependency: Validates package requirements
Home-page: https://github.com/k-homma/pypipkg
Author: Kanan HOMMA
Author-email: kanan_homma@jaist.ac.jp
Maintainer: Kanan HOMMA
Maintainer-email: kanan_homma@jaist.ac.jp
License: MIT
Platform: UNKNOWN
Classifier: Programming Language :: Python :: 2
Classifier: Programming Language :: Python :: 2.7
Classifier: Programming Language :: Python :: 3
Classifier: Programming Language :: Python :: 3.7
Classifier: License :: OSI Approved :: MIT License
